chatette/__init__.py
chatette/__main__.py
chatette/configuration.py
chatette/deprecations.py
chatette/facade.py
chatette/generator.py
chatette/log.py
chatette/statistics.py
chatette/utils.py
chatette/adapters/__init__.py
chatette/adapters/_base.py
chatette/adapters/factory.py
chatette/adapters/jsonl.py
chatette/adapters/rasa.py
chatette/adapters/rasa_md.py
chatette/cli/__init__.py
chatette/cli/interpreter.py
chatette/cli/terminal_writer.py
chatette/cli/interactive_commands/__init__.py
chatette/cli/interactive_commands/add_rule_command.py
chatette/cli/interactive_commands/command_strategy.py
chatette/cli/interactive_commands/declare_command.py
chatette/cli/interactive_commands/delete_command.py
chatette/cli/interactive_commands/examples_command.py
chatette/cli/interactive_commands/execute_command.py
chatette/cli/interactive_commands/exist_command.py
chatette/cli/interactive_commands/exit_command.py
chatette/cli/interactive_commands/generate_command.py
chatette/cli/interactive_commands/hide_command.py
chatette/cli/interactive_commands/parse_command.py
chatette/cli/interactive_commands/rename_command.py
chatette/cli/interactive_commands/rule_command.py
chatette/cli/interactive_commands/save_command.py
chatette/cli/interactive_commands/set_modifier_command.py
chatette/cli/interactive_commands/show_command.py
chatette/cli/interactive_commands/stats_command.py
chatette/cli/interactive_commands/unhide_command.py
chatette/modifiers/__init__.py
chatette/modifiers/argument.py
chatette/modifiers/casegen.py
chatette/modifiers/randgen.py
chatette/modifiers/representation.py
chatette/parsing/__init__.py
chatette/parsing/input_file_manager.py
chatette/parsing/line_count_file_wrapper.py
chatette/parsing/parser.py
chatette/parsing/utils.py
chatette/parsing/lexing/__init__.py
chatette/parsing/lexing/lexer.py
chatette/parsing/lexing/lexing_rule.py
chatette/parsing/lexing/rule_annotation.py
chatette/parsing/lexing/rule_arg_assignment.py
chatette/parsing/lexing/rule_arg_decl.py
chatette-1.6.3.dist-info/LICENSE
chatette-1.6.3.dist-info/METADATA
chatette-1.6.3.dist-info/WHEEL
chatette-1.6.3.dist-info/top_level.txt
chatette-1.6.3.dist-info/RECORD
