Metadata-Version: 2.1
Name: chatette
Version: 1.6.3
Summary: A dataset generator for Rasa NLU
Home-page: https://github.com/SimGus/Chatette
Author: SimGus
License: MIT
Platform: UNKNOWN
Classifier: Programming Language :: Python :: 2.7
Classifier: Programming Language :: Python :: 3
Classifier: License :: OSI Approved :: MIT License
Classifier: Operating System :: OS Independent
Classifier: Environment :: Console
Classifier: Intended Audience :: Developers
Classifier: Topic :: Utilities
Classifier: Topic :: Text Processing
Classifier: Topic :: Communications
Requires-Dist: enum-compat
Requires-Dist: future
Requires-Dist: six
